<fest:template xmlns:fest="http://fest.mail.ru" context_name="json">
    <div class="menu">
        <div class="menu__title">
            SPACECRAFT
        </div>
        <a href="#game" class="menu__button">
            <span class="menu__button__span">
                НАЧАТЬ ИГРУ         
            </span>
        </a>
        <a href="#scoreboard" class="menu__button">
            <span class="menu__button__span">
                РЕКОРДЫ        
            </span>
        </a>
    </div>
</fest:template>
